LICENSE
README.md
setup.py
shz_geo/__init__.py
shz_geo.egg-info/PKG-INFO
shz_geo.egg-info/SOURCES.txt
shz_geo.egg-info/dependency_links.txt
shz_geo.egg-info/requires.txt
shz_geo.egg-info/top_level.txt
shz_geo/modis/__init__.py
shz_geo/modis/download_data.py
shz_geo/tools/__init__.py
shz_geo/tools/normalizeWithScaleFactor.py