Metadata-Version: 2.1
Name: shz-geo
Version: 0.1.1
Summary: Personal types for my projects
Author: Eliseu Brito
Author-email: eliseubrito776@gmail.com
License: MIT License
Keywords: shz geo shzgeo shz_geo
License-File: LICENSE
